elarodon/ONTLRcaller.py
elarodon/__init__.py
elarodon/alignment_INS.py
elarodon/define_type_create_vcf_LRs.py
elarodon/joinONTLRs.py
elarodon/main.py
elarodon/read_bam_file.py
elarodon-0.1.2.dist-info/METADATA
elarodon-0.1.2.dist-info/WHEEL
elarodon-0.1.2.dist-info/entry_points.txt
elarodon-0.1.2.dist-info/top_level.txt
elarodon-0.1.2.dist-info/RECORD
