Metadata-Version: 2.4
Name: elarodon
Version: 0.1.2
Summary: A comprehensive pipeline for detection and analysis of large genomic rearrangements from Oxford Nanopore Technologies (ONT) sequencing data.
Home-page: https://github.com/aakechin/eLaRodON
Author: Kechin A., Mikheeva R.
Author-email: mikheeva@yandex.ru
Classifier: Programming Language :: Python :: 3
Classifier: Programming Language :: Python :: 3.10
Classifier: Programming Language :: Python :: 3.11
Classifier: License :: OSI Approved :: MIT License
Classifier: Operating System :: OS Independent
Requires-Python: >=3.10
Requires-Dist: biopython==1.84
Requires-Dist: pandas==2.2.2
Requires-Dist: pysam==0.22.1
Requires-Dist: toml==0.10.2
Requires-Dist: tqdm==4.66.5
